my_lin_reg/__init__.py
my_lin_reg/regression_lineaire.py
my_lin_reg-0.4.3.dist-info/METADATA
my_lin_reg-0.4.3.dist-info/WHEEL
my_lin_reg-0.4.3.dist-info/RECORD
