Metadata-Version: 2.1
Name: my_lin_reg
Version: 0.4.3
Summary: regression linéaire
Author: Julien Zanin
Requires-Python: >=3.9,<3.13
Classifier: Programming Language :: Python :: 3
Classifier: Programming Language :: Python :: 3.9
Classifier: Programming Language :: Python :: 3.10
Classifier: Programming Language :: Python :: 3.11
Classifier: Programming Language :: Python :: 3.12
Requires-Dist: numpy (==1.26.1)
Requires-Dist: scipy (==1.11.3)
